beanstalk_example/__init__.py
beanstalk_example/beanstalk_jobs.py
beanstalk_example/management/__init__.py
beanstalk_example/management/commands/__init__.py
beanstalk_example/management/commands/beanstalk_example_client.py
django_beanstalkd/__init__.py
django_beanstalkd/decorators.py
django_beanstalkd/management/__init__.py
django_beanstalkd/management/commands/__init__.py
django_beanstalkd/management/commands/beanstalk_worker.py
django_beanstalkd-1.0.1.dist-info/DESCRIPTION.rst
django_beanstalkd-1.0.1.dist-info/METADATA
django_beanstalkd-1.0.1.dist-info/RECORD
django_beanstalkd-1.0.1.dist-info/WHEEL
django_beanstalkd-1.0.1.dist-info/metadata.json
django_beanstalkd-1.0.1.dist-info/top_level.txt
