Metadata-Version: 2.0
Name: django-beanstalkd
Version: 1.0.1
Summary: A convenience wrapper for beanstalkd clients and workers in Django using the beanstalkc library for Python
Home-page: https://github.com/beanstalkdclub/django-beanstalkd
Author: Kimi Huang
Author-email: kimi.huang@brightcells.com
License: MPL
Platform: UNKNOWN
Classifier: Development Status :: 5 - Production/Stable
Classifier: Environment :: Web Environment
Classifier: Framework :: Django
Classifier: Intended Audience :: Developers
Classifier: Operating System :: OS Independent
Classifier: Programming Language :: Python
Classifier: Topic :: Software Development :: Libraries :: Python Modules
Requires-Dist: beanstalkc
Requires-Dist: django-six
Requires-Dist: pyyaml
